[
    {
        "id":"900264732",
        "firstName": "Alice",
        "lastName": "Johnson",
        "email": "ajohnson@ggc.edu",
        "password": "VEkvMu3k"
    },
    {
        "id":"900325651",
        "firstName": "Benjamin",
        "lastName": "Parker",
        "email": "bparker@ggc.edu",
        "password": "v6TsxTGR"
    },
    {
        "id":"900792188",
        "firstName": "Charlotte",
        "lastName": "Adams",
        "email": "cadams@ggc.edu",
        "password": "wu6AYLKD"
    },
    {
        "id":"900151866",
        "firstName": "Daniel",
        "lastName": "Mitchell",
        "email": "dmitchell@ggc.edu",
        "password": "vZYs9vAY"
    },
    {
        "id":"900199224",
        "firstName": "Emily",
        "lastName": "Wilson",
        "email": "ewilson@ggc.edu",
        "password": "5yVMEZaD"
    },
    {
        "id":"900930880",
        "firstName": "Frank",
        "lastName": "Anderson",
        "email": "fanderson@ggc.edu",
        "password": "ZBzRpfBx"
    },
    {
        "id":"900713844",
        "firstName": "Grace",
        "lastName": "Turner",
        "email": "gturner@ggc.edu",
        "password": "NxLGSk6V"
    },
    {
        "id":"900020784",
        "firstName": "Henry",
        "lastName": "Roberts",
        "email": "hroberts@ggc.edu",
        "password": "55gxq4ve"
    },
    {
        "id":"900228778",
        "firstName": "Isabella",
        "lastName": "Hayes",
        "email": "ihayes@ggc.edu",
        "password": "9HvLtgva"
    },
    {
        "id":"900189102",
        "firstName": "Jack",
        "lastName": "Davis",
        "email": "jdavis@ggc.edu",
        "password": "avXdcDhC"
    },
    {
        "id":"900208448",
        "firstName": "Katherine",
        "lastName": "Lewis",
        "email": "klewis@ggc.edu",
        "password": "HeuApdfY"
    },
    {
        "id":"900348378",
        "firstName": "Liam",
        "lastName": "Thompson",
        "email": "lthompson@ggc.edu",
        "password": "AA5Ag5N6"
    },
    {
        "id":"900833552",
        "firstName": "Mia",
        "lastName": "Murphy",
        "email": "mmurphy@ggc.edu",
        "password": "5xaqap9Z"
    },
    {
        "id":"900628973",
        "firstName": "Noah",
        "lastName": "Foster",
        "email": "nfoster@ggc.edu",
        "password": "NBHC7g7v"
    },
    {
        "id":"900294544",
        "firstName": "Olivia",
        "lastName": "Brooks",
        "email": "obrooks@ggc.edu",
        "password": "a5wu3tFK"
    },
    {
        "id":"900558448",
        "firstName": "Patrick",
        "lastName": "Ward",
        "email": "pward@ggc.edu",
        "password": "xe8WzKcz"
    },
    {
        "id":"900226141",
        "firstName": "Quinn",
        "lastName": "Harrison",
        "email": "qharrison@ggc.edu",
        "password": "W5TPLGXu"
    },
    {
        "id":"900852531",
        "firstName": "Rachel",
        "lastName": "Bell",
        "email": "rbell@ggc.edu",
        "password": "re8qgfAu"
    },
    {
        "id":"900064623",
        "firstName": "Samuel",
        "lastName": "Gray",
        "email": "sgray@ggc.edu",
        "password": "rn9WLzFN"
    },
    {
        "id":"900972674",
        "firstName": "Taylor",
        "lastName": "Jenkins",
        "email": "tjenkins@ggc.edu",
        "password": "ptaWpZzd"
    },
    {
        "id":"900694252",
        "firstName": "Victoria",
        "lastName": "Carter",
        "email": "vcarter@ggc.edu",
        "password": "c6PFmxnj"
    },
    {
        "id":"900320195",
        "firstName": "William",
        "lastName": "Smith",
        "email": "wsmith@ggc.edu",
        "password": "Sra3vbjw"
    },
    {
        "id":"900614415",
        "firstName": "Zoey",
        "lastName": "Foster",
        "email": "zfoster@ggc.edu",
        "password": "bVDddG6H"
    },
    {
        "id":"900264975",
        "firstName": "Alexander",
        "lastName": "White",
        "email": "awhite@ggc.edu",
        "password": "rU8Pd2qE"
    },
    {
        "id":"900494923",
        "firstName": "Brooke",
        "lastName": "Martin",
        "email": "bmartin@ggc.edu",
        "password": "M3CwREU7"
    },
    {
        "id":"900915185",
        "firstName": "Christopher",
        "lastName": "Walker",
        "email": "cwalker@ggc.edu",
        "password": "ambDEsXF"
    },
    {
        "id":"900039985",
        "firstName": "Daisy",
        "lastName": "King",
        "email": "dking@ggc.edu",
        "password": "jKWUSFnG"
    },
    {
        "id":"900581347",
        "firstName": "Ethan",
        "lastName": "Turner",
        "email": "eturner@ggc.edu",
        "password": "VPhTRbzG"
    },
    {
        "id":"900932111",
        "firstName": "Fiona",
        "lastName": "Green",
        "email": "fgreen@ggc.edu",
        "password": "9CUK6RZL"
    },
    {
        "id":"900255276",
        "firstName": "George",
        "lastName": "Mitchell",
        "email": "gmitchell@ggc.edu",
        "password": "afptvJXp"
    },
    {
        "id":"900314499",
        "firstName": "Hannah",
        "lastName": "Baker",
        "email": "hbaker@ggc.edu",
        "password": "6D7c9Crn"
    },
    {
        "id":"900504781",
        "firstName": "Isaac",
        "lastName": "Reed",
        "email": "ireed@ggc.edu",
        "password": "EYBAGzyz"
    },
    {
        "id":"900607829",
        "firstName": "Jasmine",
        "lastName": "Hall",
        "email": "jhall@ggc.edu",
        "password": "sPHZkKw8"
    },
    {
        "id":"900573399",
        "firstName": "Kevin",
        "lastName": "Turner",
        "email": "kturner@ggc.edu",
        "password": "hUBABTP8"
    },
    {
        "id":"900388185",
        "firstName": "Lily",
        "lastName": "Adams",
        "email": "ladams@ggc.edu",
        "password": "rWpXXt8p"
    },
    {
        "id":"900254651",
        "firstName": "Michael",
        "lastName": "Brown",
        "email": "mbrown@ggc.edu",
        "password": "arm96THW"
    },
    {
        "id":"900254652",
        "firstName": "Natalie",
        "lastName": "Parker",
        "email": "nparker@ggc.edu",
        "password": "UBtmKGxY"
    },
    {
        "id":"900441075",
        "firstName": "Owen",
        "lastName": "Bennett",
        "email": "obennett@ggc.edu",
        "password": "6wUnxwmz"
    },
    {
        "id":"900203452",
        "firstName": "Penelope",
        "lastName": "Clark",
        "email": "pclark@ggc.edu",
        "password": "mmLNjAKK"
    },
    {
        "id":"900086033",
        "firstName": "Quentin",
        "lastName": "Hayes",
        "email": "qhayes@ggc.edu",
        "password": "94EECnDE"
    },
    {
        "id":"900839849",
        "firstName": "Ruby",
        "lastName": "Wilson",
        "email": "rwilson@ggc.edu",
        "password": "QphR7Mr6"
    },
    {
        "id":"900753393",
        "firstName": "Sebastian",
        "lastName": "Hill",
        "email": "shill@ggc.edu",
        "password": "CeCBZDNj"
    },
    {
        "id":"900073373",
        "firstName": "Taylor",
        "lastName": "Evans",
        "email": "tevans@ggc.edu",
        "password": "Hgk77hvx"
    },
    {
        "id":"900036159",
        "firstName": "Ulysses",
        "lastName": "Roberts",
        "email": "uroberts@ggc.edu",
        "password": "hK9rssWL"
    },
    {
        "id":"900473416",
        "firstName": "Violet",
        "lastName": "Campbell",
        "email": "vcampbell@ggc.edu",
        "password": "gDKKJ8KR"
    },
    {
        "id":"900574033",
        "firstName": "Wlater",
        "lastName": "Morris",
        "email": "wmorris@ggc.edu",
        "password": "qX5Mbb2w"
    },
    {
        "id":"900610443",
        "firstName": "Xander",
        "lastName": "Reed",
        "email": "xreed@ggc.edu",
        "password": "PD9JuvVN"
    },
    {
        "id":"900291788",
        "firstName": "Yasmine",
        "lastName": "Martinez",
        "email": "ymartinez@ggc.edu",
        "password": "xUaDEVaF"
    },
    {
        "id":"900029169",
        "firstName": "Zachary",
        "lastName": "Johnson",
        "email": "zjohnson@ggc.edu",
        "password": "xXvseZNx"
    },
    {
        "id":"900554380",
        "firstName": "Zoe",
        "lastName": "Anderson",
        "email": "zanderson@ggc.edu",
        "password": "cxfSdSNV"
    }
]